readable_passcode/__init__.py
readable_passcode/readable_passcode.py
readable_passcode/words.txt
readable_passcode-1.0.1.dist-info/LICENSE
readable_passcode-1.0.1.dist-info/METADATA
readable_passcode-1.0.1.dist-info/WHEEL
readable_passcode-1.0.1.dist-info/entry_points.txt
readable_passcode-1.0.1.dist-info/top_level.txt
readable_passcode-1.0.1.dist-info/RECORD
