Metadata-Version: 2.1
Name: readable-passcode
Version: 1.0.1
Summary: Generate human-readable passcodes with memory optimization
Home-page: https://github.com/dedenbangkit/readable-passcode
Author: Deden
Author-email: mail@dedenbangkit.com
Project-URL: Documentation, https://github.com/dedenbangkit/readable-passcode
Project-URL: Bug Reports, https://github.com/dedenbangkit/readable-passcode/issues
Project-URL: Source Code, https://github.com/dedenbangkit/readable-passcode
Classifier: Intended Audience :: Developers
Classifier: Programming Language :: Python :: 3.8
Classifier: Programming Language :: Python :: 3.9
Classifier: Programming Language :: Python :: 3.10
Classifier: Programming Language :: Python :: 3 :: Only
Classifier: License :: OSI Approved :: GNU Affero General Public License v3
Classifier: License :: OSI Approved :: MIT License
Classifier: Operating System :: OS Independent
Requires-Python: >=3.8
License-File: LICENSE
Provides-Extra: dev
Requires-Dist: check-manifest ; extra == 'dev'
